Metadata-Version: 1.0
Name: panhello
Version: 0.0.4
Summary: This is a pan hello package.
Home-page: https://pypi.python.org/pypi/panhello
Author: Cppowboy
Author-email: panyx93@163.com
License: MIT
Keywords: test hello
Platform: UNKNOWN
